pymentor/__init__.py
pymentor/error.py
pymentor/mentor.py
pymentor-0.1.1.data/scripts/error.py
pymentor-0.1.1.data/scripts/mentor.py
pymentor-0.1.1.dist-info/LICENSE
pymentor-0.1.1.dist-info/METADATA
pymentor-0.1.1.dist-info/WHEEL
pymentor-0.1.1.dist-info/top_level.txt
pymentor-0.1.1.dist-info/RECORD
