Metadata-Version: 2.1
Name: pymentor
Version: 0.1.1
Summary: A package to implement a computational model of Mentor didactic robotic arm.
Home-page: https://github.com/oscarkremer/pymentor
Author: Oscar Schmitt Kremer
Author-email: oscar.s.kremer@hotmail.com
License: UNKNOWN
Platform: UNKNOWN
Classifier: Programming Language :: Python :: 3
Classifier: Operating System :: OS Independent
License-File: LICENSE
Requires-Dist: numpy
Requires-Dist: pytest
